taln2x/__init__.py
taln2x/__main__.py
taln2x/exports/__init__.py
taln2x/exports/anthology.py
taln2x/exports/archives.py
taln2x/exports/dblp.py
taln2x/exports/hal.py
taln2x/exports/pdf.py
taln2x/templates/PDFBox-0.7.3.jar
taln2x/templates/aofr.xsd
taln2x/templates/articles.csv
taln2x/templates/articles.zip
taln2x/templates/author_list.xlsx
taln2x/templates/background.png
taln2x/templates/blank.pdf
taln2x/templates/by.eps
taln2x/templates/config.toml
taln2x/templates/dblpsubmission.dtd
taln2x/templates/easy2acl.py
taln2x/templates/event.yml
taln2x/templates/logo.png
taln2x/templates/pre-proceedings-en.tex
taln2x/templates/pre-proceedings.tex
taln2x/templates/single_paper.tex
taln2x/templates/taln-archives.xsd
taln2x/utils/Article.py
taln2x/utils/Author.py
taln2x/utils/Event.py
taln2x/utils/Track.py
taln2x/utils/__init__.py
taln2x/utils/archives.py
taln2x/utils/easychair.py
taln2x/utils/readevent.py
taln2x/utils/readpdf.py
taln2x/utils/sciencesconf.py
taln2x/utils/searchid.py
taln2x/utils/taln_archives_parser.py
taln2x-1.0.10.dist-info/LICENCE
taln2x-1.0.10.dist-info/METADATA
taln2x-1.0.10.dist-info/WHEEL
taln2x-1.0.10.dist-info/entry_points.txt
taln2x-1.0.10.dist-info/top_level.txt
taln2x-1.0.10.dist-info/RECORD
