Metadata-Version: 2.1
Name: taln2x
Version: 1.0.10
Summary: A command-line application to export (TALN-like) conference proceedings to various formats (namely pdf, hal, aclanthology, dblp)
Author-email: Yannick Parmentier <yannick.parmentier@gmail.com>
Project-URL: Homepage, https://gitlab.inria.fr/talnarchives/taln2x
Project-URL: Bug Tracker, https://gitlab.inria.fr/talnarchives/taln2x/-/issues
Keywords: taln,atala,paper,publication,open archive
Classifier: Programming Language :: Python :: 3
Classifier: License :: OSI Approved :: GNU General Public License v3 or later (GPLv3+)
Classifier: Operating System :: OS Independent
Requires-Python: >=3.10
License-File: LICENCE
Requires-Dist: click
Requires-Dist: openpyxl
Requires-Dist: nameparser
Requires-Dist: langdetect
Requires-Dist: pylatexenc
Requires-Dist: unidecode
Requires-Dist: pybtex
Requires-Dist: pypdf
Requires-Dist: pycountry
Requires-Dist: xmlschema
Requires-Dist: tqdm
Requires-Dist: lxml
Requires-Dist: beautifulsoup4
Requires-Dist: country-list
Requires-Dist: tomlkit
